[{"name":"Plateau Motors","phone_number":"(425) 898-9900","address":"625 228th Ave NE Sammamish, WA 98074","city":"sammamish","page":0,"url":"https:\/\/www.yelp.com\/biz\/plateau-motors-sammamish"},{"name":"Stingray Auto Repair","phone_number":"(425) 836-7466","address":"22647 NE Redmond Fall City Rd Redmond, WA 98053","city":"sammamish","page":0,"url":"https:\/\/www.yelp.com\/biz\/stingray-auto-repair-redmond"},{"name":"Morgan Motors","phone_number":"(425) 391-3600","address":"1430 NW Mall St Ste C Issaquah, WA 98027","city":"sammamish","page":0,"url":"https:\/\/www.yelp.com\/biz\/morgan-motors-issaquah"},{"name":"Michael\u2019s Auto Repair","phone_number":"(425) 869-2419","address":"17443 NE 70th St Redmond, WA 98052","city":"sammamish","page":0,"url":"https:\/\/www.yelp.com\/biz\/michaels-auto-repair-redmond"},{"name":"East Side Auto Care","phone_number":"(425) 861-7777","address":"17525 NE 67th Ct Redmond, WA 98052","city":"sammamish","page":0,"url":"https:\/\/www.yelp.com\/biz\/east-side-auto-care-redmond"},{"name":"Eastside Bavarian","phone_number":"(425) 391-1990","address":"6010 221st Pl SE Issaquah, WA 98027","city":"sammamish","page":0,"url":"https:\/\/www.yelp.com\/biz\/eastside-bavarian-issaquah"},{"name":"Eschen Automotive","phone_number":"(425) 456-0466","address":"12005 NE 12th St Ste 14 Bellevue, WA 98005","city":"sammamish","page":0,"url":"https:\/\/www.yelp.com\/biz\/eschen-automotive-bellevue-2"},{"name":"AA Auto Service Center","phone_number":"(425) 305-2204","address":"8004 Avondale Way NE Redmond, WA 98052","city":"sammamish","page":0,"url":"https:\/\/www.yelp.com\/biz\/aa-auto-service-center-redmond"},{"name":"Tru-Line Bellevue","phone_number":"(425) 462-0013","address":"1423 130th Ave NE Bellevue, WA 98005","city":"sammamish","page":0,"url":"https:\/\/www.yelp.com\/biz\/tru-line-bellevue-bellevue-2"},{"name":"Europa Imported Service","phone_number":"(425) 454-1432","address":"12700 Bel-red Rd Bellevue, WA 98005","city":"sammamish","page":0,"url":"https:\/\/www.yelp.com\/biz\/europa-imported-service-bellevue-3"}]